ml4climate/__init__.py
ml4climate/_config.yml
ml4climate/_toc.yml
ml4climate/general_intro.pdf
ml4climate/chapters/frontmatter.md
ml4climate/chapters/resources.md
ml4climate/images/logos/logo_cnrs.png
ml4climate/images/logos/logo_e4c_final.png
ml4climate/images/logos/logo_ens.jpg
ml4climate/images/logos/logo_ep.png
ml4climate/images/logos/logo_ipsl.png
ml4climate/images/logos/logo_lmd.jpg
ml4climate/images/logos/logo_su.png
ml4climate/images/notebooks_guide/download_with_browser.png
ml4climate/images/notebooks_guide/install_extension.png
ml4climate/images/notebooks_guide/install_packages.png
ml4climate/images/notebooks_guide/login.png
ml4climate/images/notebooks_guide/open_notebook.png
ml4climate/images/notebooks_guide/open_terminal.png
ml4climate/notebooks/00_content.ipynb
ml4climate/notebooks/01_introduction.ipynb
ml4climate/notebooks/01_tutorial_introduction.ipynb
ml4climate/notebooks/02_supervised_learning_problem.ipynb
ml4climate/notebooks/02_tutorial_supervised_learning_problem_ols.ipynb
ml4climate/notebooks/03_ordinary_least_squares.ipynb
ml4climate/notebooks/04_overfitting_underfitting_bias_variance.ipynb
ml4climate/notebooks/04_tutorial_overfitting_underfitting_bias_variance.ipynb
ml4climate/notebooks/05_regularization_selection_evaluation.ipynb
ml4climate/notebooks/05_tutorial_regularization_selection_evaluation.ipynb
ml4climate/notebooks/06_classification_generative.ipynb
ml4climate/notebooks/06_tutorial_classification_generative.ipynb
ml4climate/notebooks/07_classification_discriminative.ipynb
ml4climate/notebooks/07_tutorial_classification_discriminative.ipynb
ml4climate/notebooks/08_tutorial_unsupervised_learning_pca.ipynb
ml4climate/notebooks/08_unsupervised_learning_pca.ipynb
ml4climate/notebooks/09_ensemble_methods.ipynb
ml4climate/notebooks/09_tutorial_ensemble_methods_demand_prediction.ipynb
ml4climate/notebooks/09_tutorial_ensemble_methods_windcf_prediction.ipynb
ml4climate/notebooks/10_neural_networks.ipynb
ml4climate-25.0.1.dist-info/licenses/LICENSE.txt
ml4climate-25.0.1.dist-info/WHEEL
ml4climate-25.0.1.dist-info/METADATA
ml4climate-25.0.1.dist-info/RECORD
