Metadata-Version: 2.4
Name: ml4climate
Version: 25.0.1
Summary: A collection of jupyter notebook to learn machine learning
Author-email: Bruno Deremble <author@example.com>, Alexis Tantet <author@example.com>, Victor Pellet <author@example.com>
Requires-Python: >=3.9
License-Expression: MIT
Classifier: Programming Language :: Python :: 3
Classifier: Operating System :: OS Independent
License-File: LICENSE.txt
Requires-Dist: matplotlib
Requires-Dist: netcdf4 >=1.5.6
Requires-Dist: numpy
Requires-Dist: pandas >=1.2.4
Requires-Dist: scipy
Requires-Dist: scikit-learn >=1.0
Requires-Dist: xarray
Project-URL: Homepage, https://github.com/mec557/ml4climate
Project-URL: Issues, https://github.com/mec557/ml4climate/issues
